{
  "plugins": {
    "gruvbox.nvim": {
      "rev": "154eb5ff5b96d0641307113fa385eaf0d36d9796",
      "src": "https://github.com/ellisonleao/gruvbox.nvim"
    },
    "halberd.nvim": {
      "rev": "45263c95b6acaf2ac44fe7bda08d916d4d29e2d3",
      "src": "https://codeberg.org/WaspByte/halberd.nvim"
    },
    "lasso.nvim": {
      "rev": "d2b4c8a7d94a24864a40467e7ac72f137c828c52",
      "src": "https://github.com/niqodea/lasso.nvim"
    },
    "mini.icons": {
      "rev": "bac6317300e205335df425296570d84322730067",
      "src": "https://github.com/echasnovski/mini.icons"
    },
    "nvim-lspconfig": {
      "rev": "21db1fd40cbcbf1524ae154ab8f394fdf085749a",
      "src": "https://github.com/neovim/nvim-lspconfig"
    },
    "oil.nvim": {
      "rev": "0fcc83805ad11cf714a949c98c605ed717e0b83e",
      "src": "https://github.com/stevearc/oil.nvim"
    },
    "plenary.nvim": {
      "rev": "74b06c6c75e4eeb3108ec01852001636d85a932b",
      "src": "https://github.com/nvim-lua/plenary.nvim"
    },
    "telescope.nvim": {
      "rev": "506338434fec5ad19cb1f8d45bf92d66c4917393",
      "src": "https://github.com/nvim-telescope/telescope.nvim"
    },
    "tree-sitter-manager.nvim": {
      "rev": "33a94d022e3a5a500d878b784ba7fec61559c70a",
      "src": "https://github.com/romus204/tree-sitter-manager.nvim"
    }
  }
}
